jetpy.helpers-0.0.0-py3.6-nspkg.pth
jetpy.helpers-0.0.0.dist-info/top_level.txt
jetpy.helpers-0.0.0.dist-info/WHEEL
jetpy.helpers-0.0.0.dist-info/METADATA
jetpy.helpers-0.0.0.dist-info/namespace_packages.txt
jetpy.helpers-0.0.0.dist-info/RECORD
jetpy.helpers-0.0.0.dist-info/metadata.json
jetpy.helpers-0.0.0.dist-info/DESCRIPTION.rst
jetpy/helpers/__init__.py
