Metadata-Version: 2.0
Name: jetpy.helpers
Version: 0.0.0
Summary: JetPy helpers
Home-page: UNKNOWN
Author: Vitalii Maslov
Author-email: me@pyvim.com
License: MIT
Platform: UNKNOWN
